weftspace/__init__.py
weftspace/_version.py
weftspace/builder.py
weftspace/data_node.py
weftspace/data_reader.py
weftspace/data_writer.py
weftspace/loaded_node.py
weftspace/logger.py
weftspace-1.0.0.dist-info/METADATA
weftspace-1.0.0.dist-info/WHEEL
weftspace-1.0.0.dist-info/licenses/LICENSE
weftspace-1.0.0.dist-info/RECORD
