Metadata-Version: 2.4
Name: weftspace
Version: 1.0.0
Summary: Weftspace is a Python library designed to provide the maximum possible level of support for Endless Sky datafile syntax by providing not only IO functionality but also support in handling and converting parsed data.
Project-URL: Homepage, https://github.com/mOctave/weftspace
Project-URL: Repository, https://github.com/mOctave/weftspace
Author-email: mOctave <moctave31415@gmail.com>
License-Expression: AGPL-3.0-or-later
License-File: LICENSE
Classifier: Development Status :: 4 - Beta
Classifier: Intended Audience :: Developers
Classifier: License :: OSI Approved :: GNU Affero General Public License v3 or later (AGPLv3+)
Classifier: Operating System :: MacOS
Classifier: Operating System :: Microsoft :: Windows
Classifier: Operating System :: OS Independent
Classifier: Operating System :: POSIX
Classifier: Operating System :: POSIX :: Linux
Classifier: Programming Language :: Python :: 3.8
Classifier: Programming Language :: Python :: 3.9
Classifier: Programming Language :: Python :: 3.10
Classifier: Programming Language :: Python :: 3.11
Classifier: Programming Language :: Python :: 3.12
Classifier: Programming Language :: Python :: 3.13
Classifier: Topic :: File Formats
Classifier: Topic :: Games/Entertainment
Classifier: Topic :: Software Development :: Libraries :: Python Modules
Classifier: Typing :: Typed
Requires-Python: >=3.8
Provides-Extra: dev
Requires-Dist: build; extra == 'dev'
Requires-Dist: pdoc3; extra == 'dev'
Requires-Dist: pyright; extra == 'dev'
Requires-Dist: pytest; extra == 'dev'
